Workbook
Name SegmentaçãodeDados_Subscription_Type: #N/A

Sheet Assets
B3: PaletadeCores
B5: #9BC848 | C5: XboxColor | E5: #E8E6E9 | F5: negativezone
B6: #22C55E | C6: XboxColor
B7: #2AE6B1 | C7: Menus
B8: #5BF6A8 | C8: Menus
B12: Logos | I12: Ícones

Sheet Base
A1: Subscriber ID | B1: Name | C1: Plan | D1: Start Date | E1: Auto Renewal | F1: Subscription Price | G1: Subscription Type | H1: EA Play Season Pass | I1: EA Play Season Pass Price | J1: Minecraft Season Pass | K1: Minecraft Season Pass Price | L1: Total Value Without Coupon | M1: Coupon Value | N1: Total Value
A2: 3231 | B2: João Silva | C2: Ultimate | D2: 45292 | E2: Yes | F2: 15 | G2: Monthly | H2: Yes | I2: 30 | J2: Yes | K2: 20 | L2: =SUM(F2,I2,K2) -> 65 | M2: 5 | N2: 60
A3: 3234 | B3: Ana Souza | C3: Ultimate | D3: 45342 | E3: No | F3: 15 | G3: Monthly | H3: Yes | I3: 30 | J3: Yes | K3: 20 | L3: =SUM(F3,I3,K3) -> 65 | M3: 3 | N3: 62
A4: 3237 | B4: Camila Ribeiro | C4: Ultimate | D4: 45354 | E4: Yes | F4: 15 | G4: Quarterly | H4: Yes | I4: 30 | J4: Yes | K4: 20 | L4: =SUM(F4,I4,K4) -> 65 | M4: 10 | N4: 55
A5: 3239 | B5: Sofia Almeida | C5: Ultimate | D5: 45356 | E5: No | F5: 15 | G5: Monthly | H5: Yes | I5: 30 | J5: Yes | K5: 20 | L5: =SUM(F5,I5,K5) -> 65 | M5: 5 | N5: 60
A6: 3242 | B6: Marco Túlio | C6: Ultimate | D6: 45359 | E6: Yes | F6: 15 | G6: Annual | H6: Yes | I6: 30 | J6: Yes | K6: 20 | L6: =SUM(F6,I6,K6) -> 65 | M6: 20 | N6: 45
A7: 3245 | B7: Fernanda Lima | C7: Ultimate | D7: 45362 | E7: No | F7: 15 | G7: Monthly | H7: Yes | I7: 30 | J7: Yes | K7: 20 | L7: =SUM(F7,I7,K7) -> 65 | M7: 8 | N7: 57
A8: 3248 | B8: Cesar Oliveira | C8: Ultimate | D8: 45365 | E8: Yes | F8: 15 | G8: Quarterly | H8: Yes | I8: 30 | J8: Yes | K8: 20 | L8: =SUM(F8,I8,K8) -> 65 | M8: 7 | N8: 58
A9: 3251 | B9: Gabriela Santos | C9: Ultimate | D9: 45368 | E9: No | F9: 15 | G9: Monthly | H9: Yes | I9: 30 | J9: Yes | K9: 20 | L9: =SUM(F9,I9,K9) -> 65 | M9: 3 | N9: 62
A10: 3254 | B10: Joaquim Barbosa | C10: Ultimate | D10: 45371 | E10: Yes | F10: 15 | G10: Annual | H10: Yes | I10: 30 | J10: Yes | K10: 20 | L10: =SUM(F10,I10,K10) -> 65 | M10: 20 | N10: 45
A11: 3257 | B11: Nicole Costa | C11: Ultimate | D11: 45374 | E11: No | F11: 15 | G11: Monthly | H11: Yes | I11: 30 | J11: Yes | K11: 20 | L11: =SUM(F11,I11,K11) -> 65 | M11: 5 | N11: 60
A12: 3260 | B12: Raquel Alves | C12: Ultimate | D12: 45377 | E12: Yes | F12: 15 | G12: Quarterly | H12: Yes | I12: 30 | J12: Yes | K12: 20 | L12: =SUM(F12,I12,K12) -> 65 | M12: 7 | N12: 58
A13: 3263 | B13: Vinicius Lima | C13: Ultimate | D13: 45380 | E13: No | F13: 15 | G13: Monthly | H13: Yes | I13: 30 | J13: Yes | K13: 20 | L13: =SUM(F13,I13,K13) -> 65 | M13: 3 | N13: 62
... A99: 3523 | B99: Carla Siqueira | C99: Ultimate | D99: 45640 | E99: No | F99: 15 | G99: Monthly | H99: Yes | I99: 30 | J99: Yes | K99: 20 | L99: =SUM(F99,I99,K99) -> 65 | M99: 3 | N99: 62

Sheet Calculos
B3: Pergunta de Negócio 1 - Qual é o Faturamento Total de Vendas de planos anuais contendo todas as assinaturar agregadas?
B4: Pergunta de Negócio 2 - Qual é o Faturamento Total de Vendas de planos anuais, separado por com e sem autorenovação?
B6: Subscription Type | C6: (Tudo)
B8: Rótulos de Linha | C8: Soma de Total Value
B9: No | C9: 2679
B10: Yes | C10: 2709
B11: Total Geral | C11: 5388
B14: Pergunta de Negócio 3 - Total de Vendas de assinatura do EA PLAY
B17: Subscription Type | C17: (Tudo)
B19: Rótulos de Linha | C19: Soma de EA Play Season Pass Price
B20: Ultimate | C20: 2940
B21: Total Geral | C21: 2940 | E21: =GETPIVOTDATA("EA Play Season Pass Price",$B$19) -> 2940
B25: Pergunta de Negócio 4 - Total de Vendas de assinatura do Minecraft Season Pass
B28: Subscription Type | C28: (Tudo)
B30: Rótulos de Linha | C30: Soma de Minecraft Season Pass Price
B31: Ultimate | C31: 1960
B32: Total Geral | C32: 1960 | E32: =GETPIVOTDATA("Minecraft Season Pass Price",$B$30) -> 1960
B35: Pergunta de Negócio 5 - Quanto do faturamento foi sem e com desconto?
B38: Subscription Type | C38: (Tudo)
B40: Soma de Total Value Without Coupon | C40: Soma de Total Value
B41: 6370 | C41: 5388 | E41: =GETPIVOTDATA("Soma de Total Value Without Coupon",$B$40)-GETPIVOTDATA("Soma de Total Value",$B$40) -> 982
E43: =GETPIVOTDATA("Soma de Total Value",$B$40)/GETPIVOTDATA("Soma de Total Value Without Coupon",$B$40)-1 -> -0.15416013
B45: Pergunta de Negócio 6 - Quanto que cada assinatura representa da receita total?
B48: Subscription Type | C48: (Tudo)
B50: Soma de Total Value Without Coupon | C50: Soma de Subscription Price | D50: Soma de Minecraft Season Pass Price | E50: Soma de EA Play Season Pass sum
B51: 6370 | C51: 1470 | D51: 1960 | E51: 2940
B53: EA PLAY COMPOSITION | C53: =IFERROR(GETPIVOTDATA("Soma de EA Play Season Pass sum",$B$50)/GETPIVOTDATA("Soma de Total Value Without Coupon",$B$50),0) -> 0.46153846
B54: Minecraft SEASON PASS COMPOSITION | C54: =IFERROR(GETPIVOTDATA("Soma de Minecraft Season Pass Price",$B$50)/GETPIVOTDATA("Soma de Total Value Without Coupon",$B$50),0) -> 0.30769231
B55: ULTIMATE BASE COMPOSITION | C55: =IFERROR(GETPIVOTDATA("Soma de Subscription Price",$B$50)/GETPIVOTDATA("Soma de Total Value Without Coupon",$B$50),0) -> 0.23076923
C56: =SUM(C53:C55) -> 1

Sheet Dashboard
C2: XBOX GAMEPASS SUBSCRIPTION SALES
C4: Reporting Period: 01/01/2024 - 31/12/2024 | Last Updated: 14/10/2026 14:47:00
A6: > Welcome, User!
R8: ="EA PLAY R$ "&GETPIVOTDATA("Soma de EA Play Season Pass sum",Calculos!$B$50) -> EA PLAY R$ 2940 | S8: =Calculos!C53 -> 0.46153846
R9: ="MINECRAFT R$ "&GETPIVOTDATA("Soma de Minecraft Season Pass Price",Calculos!$B$50) -> MINECRAFT R$ 1960 | S9: =Calculos!C54 -> 0.30769231
R10: ="ULTIMATE BASE R$ "&GETPIVOTDATA("Soma de Subscription Price",Calculos!$B$50) -> ULTIMATE BASE R$ 1470 | S10: =Calculos!C55 -> 0.23076923
R11: TOTAL BEFORE COUPONS
R12: TOTAL (R$) | S12: =GETPIVOTDATA("Soma de Total Value Without Coupon",Calculos!$B$50) -> 6370
R13: BEFORE COUPONS | COMPOSITION = 100%
